main.py
cli/__init__.py
cli/main.py
cli/commands/__init__.py
cli/commands/animation.py
cli/commands/asset.py
cli/commands/audio.py
cli/commands/batch.py
cli/commands/code.py
cli/commands/component.py
cli/commands/editor.py
cli/commands/gameobject.py
cli/commands/instance.py
cli/commands/lighting.py
cli/commands/material.py
cli/commands/prefab.py
cli/commands/scene.py
cli/commands/script.py
cli/commands/shader.py
cli/commands/texture.py
cli/commands/tool.py
cli/commands/ui.py
cli/commands/vfx.py
cli/utils/__init__.py
cli/utils/config.py
cli/utils/confirmation.py
cli/utils/connection.py
cli/utils/constants.py
cli/utils/output.py
cli/utils/parsers.py
cli/utils/suggestions.py
core/__init__.py
core/config.py
core/constants.py
core/logging_decorator.py
core/telemetry.py
core/telemetry_decorator.py
mcpforunityserver-9.3.1.dist-info/licenses/LICENSE
models/__init__.py
models/models.py
models/unity_response.py
services/__init__.py
services/api_key_service.py
services/custom_tool_service.py
services/registry/__init__.py
services/registry/resource_registry.py
services/registry/tool_registry.py
services/resources/__init__.py
services/resources/active_tool.py
services/resources/custom_tools.py
services/resources/editor_state.py
services/resources/gameobject.py
services/resources/layers.py
services/resources/menu_items.py
services/resources/prefab.py
services/resources/prefab_stage.py
services/resources/project_info.py
services/resources/selection.py
services/resources/tags.py
services/resources/tests.py
services/resources/unity_instances.py
services/resources/windows.py
services/state/external_changes_scanner.py
services/tools/__init__.py
services/tools/batch_execute.py
services/tools/debug_request_context.py
services/tools/execute_custom_tool.py
services/tools/execute_menu_item.py
services/tools/find_gameobjects.py
services/tools/find_in_file.py
services/tools/manage_asset.py
services/tools/manage_components.py
services/tools/manage_editor.py
services/tools/manage_gameobject.py
services/tools/manage_material.py
mcpforunityserver-9.3.1.dist-info/METADATA
mcpforunityserver-9.3.1.dist-info/WHEEL
mcpforunityserver-9.3.1.dist-info/entry_points.txt
mcpforunityserver-9.3.1.dist-info/top_level.txt
mcpforunityserver-9.3.1.dist-info/RECORD
