Metadata-Version: 2.4
Name: mcpforunityserver
Version: 9.3.1
Summary: MCP for Unity Server: A Unity package for Unity Editor integration via the Model Context Protocol (MCP).
Author-email: Marcus Sanatan <msanatan@gmail.com>, David Sarno <david.sarno@gmail.com>, Wu Shutong <martinwfire@gmail.com>
License-Expression: MIT
Project-URL: Repository, https://github.com/CoplayDev/unity-mcp.git
Project-URL: Issues, https://github.com/CoplayDev/unity-mcp/issues
Keywords: mcp,unity,ai,model context protocol,gamedev,unity3d,automation,llm,agent
Classifier: Development Status :: 5 - Production/Stable
Classifier: Environment :: Console
Classifier: Intended Audience :: Developers
Classifier: Natural Language :: English
Classifier: Programming Language :: Python :: 3
Classifier: Programming Language :: Python :: 3.10
Classifier: Programming Language :: Python :: 3.11
Classifier: Programming Language :: Python :: 3.12
Classifier: Programming Language :: Python :: 3.13
Classifier: Programming Language :: Python :: 3.14
Classifier: Programming Language :: Python :: Implementation :: CPython
Classifier: Topic :: Internet :: WWW/HTTP :: HTTP Servers
Classifier: Topic :: Software Development :: Libraries :: Python Modules
Classifier: Topic :: Games/Entertainment
Classifier: Topic :: Software Development :: Code Generators
Requires-Python: >=3.10
License-File: LICENSE
Requires-Dist: httpx>=0.27.2
Requires-Dist: fastmcp==2.14.1
Requires-Dist: mcp>=1.16.0
Requires-Dist: pydantic>=2.12.5
Requires-Dist: tomli>=2.3.0
Requires-Dist: fastapi>=0.104.0
Requires-Dist: uvicorn>=0.35.0
Requires-Dist: click>=8.1.0
Provides-Extra: dev
Requires-Dist: pytest>=8.0.0; extra == "dev"
Requires-Dist: pytest-asyncio>=0.23; extra == "dev"
Requires-Dist: pytest-cov>=4.1.0; extra == "dev"
Dynamic: license-file
